{"protocol": "NSO", "links": [{"source": "0x100000000000000L", "cost": 0.5280351576601644, "target": "0x2100000000000000L", "properties": {"interface": "0x0", "link_quality": 1}}, {"source": "0x100000000000000L", "cost": 0.6700234565224555, "target": "0x2200000000000000L", "properties": {"interface": "0x0", "link_quality": 1}}, {"source": "0x100000000000000L", "cost": 0.6055648358718081, "target": "0x2000000000000000L", "properties": {"interface": "0x0", "link_quality": 1}}, {"source": "0x2100000000000000L", "cost": 0.9113448932139933, "target": "0x100000000000000L", "properties": {"interface": "0x0", "link_quality": 1}}, {"source": "0x2100000000000000L", "cost": 0.5653698061666169, "target": "0x2200000000000000L", "properties": {"interface": "0x0", "link_quality": 1}}, {"source": "0x2100000000000000L", "cost": 0.10762017078775055, "target": "0x2000000000000000L", "properties": {"interface": "0x0", "link_quality": 1}}, {"source": "0x2200000000000000L", "cost": 0.6985659650671724, "target": "0x2100000000000000L", "properties": {"interface": "0x0", "link_quality": 1}}, {"source": "0x2200000000000000L", "cost": 0.051023561094558634, "target": "0x100000000000000L", "properties": {"interface": "0x0", "link_quality": 1}}, {"source": "0x2200000000000000L", "cost": 0.278660190349472, "target": "0x2000000000000000L", "properties": {"interface": "0x0", "link_quality": 1}}, {"source": "0x2000000000000000L", "cost": 0.33366277107664866, "target": "0x100000000000000L", "properties": {"interface": "0x0", "link_quality": 1}}, {"source": "0x2000000000000000L", "cost": 0.20175805084914888, "target": "0x2100000000000000L", "properties": {"interface": "0x0", "link_quality": 1}}, {"source": "0x2000000000000000L", "cost": 0.16335244294648543, "target": "0x2200000000000000L", "properties": {"interface": "0x0", "link_quality": 1}}], "metric": "shortest path", "version": "1", "nodes": [{"properties": {"battery": 100, "nbrs_lst": ["0x2100000000000000L", "0x2200000000000000L", "0x2000000000000000L"], "interfaces": 1, "base_station": true, "neigbours": 3}, "id": "0x100000000000000L", "label": null}, {"properties": {"battery": 100, "nbrs_lst": ["0x100000000000000L", "0x2200000000000000L", "0x2000000000000000L"], "interfaces": 1, "base_station": false, "neigbours": 3}, "id": "0x2100000000000000L", "label": null}, {"properties": {"battery": 100, "nbrs_lst": ["0x2100000000000000L", "0x100000000000000L", "0x2000000000000000L"], "interfaces": 1, "base_station": false, "neigbours": 3}, "id": "0x2200000000000000L", "label": null}, {"properties": {"battery": 100, "nbrs_lst": ["0x100000000000000L", "0x2100000000000000L", "0x2200000000000000L"], "interfaces": 1, "base_station": false, "neigbours": 3}, "id": "0x2000000000000000L", "label": null}], "type": "NetworkGraph", "topology_id": "0xf1257"}